score.tpl-0.3.12-py3.7-nspkg.pth
score/tpl/__init__.py
score/tpl/_exc.py
score/tpl/_init.py
score/tpl/loader.py
score/tpl/renderer.py
score.tpl-0.3.12.dist-info/COPYING.LESSER.txt
score.tpl-0.3.12.dist-info/METADATA
score.tpl-0.3.12.dist-info/WHEEL
score.tpl-0.3.12.dist-info/namespace_packages.txt
score.tpl-0.3.12.dist-info/top_level.txt
score.tpl-0.3.12.dist-info/RECORD
